venvflon/__init__.py
venvflon/flon.py
venvflon/py.typed
venvflon/run.py
venvflon/utils.py
venvflon/img/cannula.ico
venvflon/img/cannula_512.png
venvflon/img/cannula_64.png
venvflon-0.7.1.dist-info/licenses/LICENSE
venvflon-0.7.1.dist-info/METADATA
venvflon-0.7.1.dist-info/WHEEL
venvflon-0.7.1.dist-info/entry_points.txt
venvflon-0.7.1.dist-info/top_level.txt
venvflon-0.7.1.dist-info/RECORD
