Metadata-Version: 2.4
Name: venvflon
Version: 0.7.1
Summary: simple virtual environment switcher
Author: Michal Plichta
Maintainer: Michal Plichta
License: MIT License
Project-URL: Homepage, https://github.com/emcek/venvflon
Project-URL: Source, https://github.com/emcek/venvflon.git
Project-URL: Changelog, https://github.com/emcek/venvflon/blob/master/CHANGELOG.md
Keywords: venv,uv,virtualenv
Classifier: Development Status :: 4 - Beta
Classifier: Environment :: Console
Classifier: Environment :: Win32 (MS Windows)
Classifier: License :: OSI Approved :: MIT License
Classifier: Programming Language :: Python :: 3.9
Classifier: Programming Language :: Python :: 3.10
Classifier: Programming Language :: Python :: 3.11
Classifier: Programming Language :: Python :: 3.12
Classifier: Programming Language :: Python :: 3.13
Classifier: Operating System :: Microsoft :: Windows
Classifier: Operating System :: Microsoft :: Windows :: Windows 10
Classifier: Operating System :: Microsoft :: Windows :: Windows 11
Classifier: Topic :: Utilities
Requires-Python: >=3.9
License-File: LICENSE
Requires-Dist: pyyaml==6.0.2
Requires-Dist: tkinterdnd2==0.4.3
Provides-Extra: test
Requires-Dist: GitPython==3.1.44; extra == "test"
Requires-Dist: interrogate==1.7.0; extra == "test"
Requires-Dist: isort==6.0.1; extra == "test"
Requires-Dist: lxml==5.3.2; extra == "test"
Requires-Dist: mypy==1.15.0; extra == "test"
Requires-Dist: packaging==24.2; extra == "test"
Requires-Dist: pip-audit==2.8.0; extra == "test"
Requires-Dist: pytest==8.3.5; extra == "test"
Requires-Dist: pytest-randomly==3.16.0; extra == "test"
Requires-Dist: ruff==0.11.4; extra == "test"
Requires-Dist: types-pyyaml==6.0.12.20250402; extra == "test"
Dynamic: license-file
